headless.py
simplemlplus-1.0.1.dist-info/METADATA
simplemlplus-1.0.1.dist-info/WHEEL
simplemlplus-1.0.1.dist-info/top_level.txt
simplemlplus-1.0.1.dist-info/RECORD
