Metadata-Version: 2.1
Name: simplemlplus
Version: 1.0.1
Summary: Simple machine learning one-liners.
Author-email: XenonPy <xenonpy@bluspace.net>
Project-URL: Homepage, https://github.com/xenonpy/ai
Keywords: ml,ai,simple
Classifier: Programming Language :: Python
Classifier: Programming Language :: Python :: 3
Requires-Python: >=3.9
Requires-Dist: scipy
Requires-Dist: scikit-learn
Requires-Dist: numpy
Requires-Dist: matplotlib
Provides-Extra: dev
Requires-Dist: pip-tools; extra == "dev"
Requires-Dist: build; extra == "dev"
Requires-Dist: twine; extra == "dev"
